agent_automata/__init__.py
agent_automata/automaton.py
agent_automata/automaton_loading.py
agent_automata/builtin_toolkit/__init__.py
agent_automata/builtin_toolkit/automaton_functions.py
agent_automata/builtin_toolkit/engines.py
agent_automata/builtin_toolkit/knowledge.py
agent_automata/builtin_toolkit/planners/__init__.py
agent_automata/builtin_toolkit/planners/prompts.yml
agent_automata/builtin_toolkit/planners/react.py
agent_automata/builtin_toolkit/reflectors.py
agent_automata/builtin_toolkit/validators.py
agent_automata/engines.py
agent_automata/knowledge.py
agent_automata/planners.py
agent_automata/reflectors.py
agent_automata/sessions.py
agent_automata/types.py
agent_automata/uncommitted/llm_function.py
agent_automata/uncommitted/old/__init__.py
agent_automata/uncommitted/old/builtin_functions.py
agent_automata/uncommitted/old/core.py
agent_automata/uncommitted/old/db/resource_metadata.db
agent_automata/uncommitted/old/engines.py
agent_automata/uncommitted/old/indexing.py
agent_automata/uncommitted/old/knowledge.py
agent_automata/uncommitted/old/llm_function.py
agent_automata/uncommitted/old/loaders.py
agent_automata/uncommitted/old/planners.py
agent_automata/uncommitted/old/prompts/automaton.yml
agent_automata/uncommitted/old/prompts/roles/uncommitted/bot.yml
agent_automata/uncommitted/old/prompts/roles/uncommitted/orchestrator.yml
agent_automata/uncommitted/old/prompts/roles/uncommitted/researcher.yml
agent_automata/uncommitted/old/prompts/roles/uncommitted/strategist.yml
agent_automata/uncommitted/old/prompts/roles/uncommitted/visionary.yml
agent_automata/uncommitted/old/prompts/roles/worker.yml
agent_automata/uncommitted/old/reasoning.py
agent_automata/uncommitted/old/reflection.py
agent_automata/uncommitted/old/resource_metadata.py
agent_automata/uncommitted/old/sessions.py
agent_automata/uncommitted/old/types.py
agent_automata/uncommitted/old/utilities/__init__.py
agent_automata/uncommitted/old/utilities/analyze_package.py
agent_automata-0.1.5.dist-info/LICENSE
agent_automata-0.1.5.dist-info/METADATA
agent_automata-0.1.5.dist-info/WHEEL
agent_automata-0.1.5.dist-info/RECORD
