Metadata-Version: 2.1
Name: agent-automata
Version: 0.1.5
Summary: 
License: MIT
Author: solarapparition
Author-email: 15233508+solarapparition@users.noreply.github.com
Requires-Python: >=3.10,<4.0
Classifier: License :: OSI Approved :: MIT License
Classifier: Programming Language :: Python :: 3
Classifier: Programming Language :: Python :: 3.10
Classifier: Programming Language :: Python :: 3.11
Provides-Extra: builtins
Requires-Dist: PyYAML (>=6.0)
Requires-Dist: langchain (>=0.0.203) ; extra == "builtins"
Requires-Dist: openai (>=0.27.4) ; extra == "builtins"
